{
  "_meta": {
    "retrieved_2nd_on": 1732765051
  },
  "all_awardings": [],
  "allow_live_comments": false,
  "approved_at_utc": null,
  "approved_by": null,
  "archived": false,
  "author": "SocialistDebateLord",
  "author_flair_background_color": null,
  "author_flair_css_class": null,
  "author_flair_richtext": [],
  "author_flair_template_id": null,
  "author_flair_text": null,
  "author_flair_text_color": null,
  "author_flair_type": "text",
  "author_fullname": "t2_ni46ggnre",
  "author_is_blocked": false,
  "author_patreon_flair": false,
  "author_premium": false,
  "awarders": [],
  "banned_at_utc": null,
  "banned_by": null,
  "can_gild": false,
  "can_mod_post": false,
  "category": null,
  "clicked": false,
  "content_categories": null,
  "contest_mode": false,
  "created": 1732635442,
  "created_utc": 1732635442,
  "discussion_type": null,
  "distinguished": null,
  "domain": "i.redd.it",
  "downs": 0,
  "edited": false,
  "gilded": 0,
  "gildings": {},
  "hidden": false,
  "hide_score": false,
  "id": "1h0eoyo",
  "is_created_from_ads_ui": false,
  "is_crosspostable": true,
  "is_meta": false,
  "is_original_content": false,
  "is_reddit_media_domain": true,
  "is_robot_indexable": true,
  "is_self": false,
  "is_video": false,
  "likes": null,
  "link_flair_background_color": "",
  "link_flair_css_class": null,
  "link_flair_richtext": [],
  "link_flair_text": null,
  "link_flair_text_color": "dark",
  "link_flair_type": "text",
  "locked": false,
  "media": null,
  "media_embed": {},
  "media_only": false,
  "mod_note": null,
  "mod_reason_by": null,
  "mod_reason_title": null,
  "mod_reports": [],
  "name": "t3_1h0eoyo",
  "no_follow": true,
  "num_comments": 218,
  "num_crossposts": 0,
  "num_reports": null,
  "over_18": false,
  "permalink": "/r/ADHDmemes/comments/1h0eoyo/youre_not_at_fault_for_anything_and_you_never_were/",
  "pinned": false,
  "post_hint": "image",
  "preview": {
    "enabled": true,
    "images": [
      {
        "id": "uHqdxYJgq4nZ9hB0OmXUQWP58Noa5AGNSzVWbzrpyBM",
        "resolutions": [
          {
            "height": 91,
            "url": "https://preview.redd.it/vrnokl7qm93e1.jpeg?width=108&crop=smart&auto=webp&s=1b57810008b9b5fcab160fe2bc38b5a6ce3242e9",
            "width": 108
          },
          {
            "height": 183,
            "url": "https://preview.redd.it/vrnokl7qm93e1.jpeg?width=216&crop=smart&auto=webp&s=ddb00fbbf0c098b991ab43652aa67d75304bdd7f",
            "width": 216
          },
          {
            "height": 271,
            "url": "https://preview.redd.it/vrnokl7qm93e1.jpeg?width=320&crop=smart&auto=webp&s=0cbdded698682b644008a343b52baba38196b8ee",
            "width": 320
          },
          {
            "height": 543,
            "url": "https://preview.redd.it/vrnokl7qm93e1.jpeg?width=640&crop=smart&auto=webp&s=744cd73b8728e75d64db8fee36dc6a19316a827f",
            "width": 640
          },
          {
            "height": 815,
            "url": "https://preview.redd.it/vrnokl7qm93e1.jpeg?width=960&crop=smart&auto=webp&s=1e1915d71888d311694a9648aa47845d2e342dcf",
            "width": 960
          },
          {
            "height": 917,
            "url": "https://preview.redd.it/vrnokl7qm93e1.jpeg?width=1080&crop=smart&auto=webp&s=7117d26446878cfdc3156a4e9266f731596db076",
            "width": 1080
          }
        ],
        "source": {
          "height": 1019,
          "url": "https://preview.redd.it/vrnokl7qm93e1.jpeg?auto=webp&s=3d81e8bdc85c2e71684309b6c4baf6eda4abb40a",
          "width": 1200
        },
        "variants": {}
      }
    ]
  },
  "pwls": null,
  "quarantine": false,
  "removal_reason": null,
  "removed_by": null,
  "removed_by_category": null,
  "report_reasons": null,
  "retrieved_on": 1732635458,
  "saved": false,
  "score": 8225,
  "secure_media": null,
  "secure_media_embed": {},
  "selftext": "",
  "send_replies": true,
  "spoiler": false,
  "stickied": false,
  "subreddit": "ADHDmemes",
  "subreddit_id": "t5_fatrt",
  "subreddit_name_prefixed": "r/ADHDmemes",
  "subreddit_subscribers": 142478,
  "subreddit_type": "public",
  "suggested_sort": null,
  "thumbnail": "https://b.thumbs.redditmedia.com/3AZO0iQxmUXedMa3wk13qQgtIVPrOPBDNPmDlM-bV_g.jpg",
  "thumbnail_height": 118,
  "thumbnail_width": 140,
  "title": "You’re not at fault for anything, and you never were",
  "top_awarded_type": null,
  "total_awards_received": 0,
  "treatment_tags": [],
  "ups": 8225,
  "upvote_ratio": 0.9599999785423279,
  "url": "https://i.redd.it/vrnokl7qm93e1.jpeg",
  "url_overridden_by_dest": "https://i.redd.it/vrnokl7qm93e1.jpeg",
  "user_reports": [],
  "view_count": null,
  "visited": false,
  "wls": null,
  "alternative_subreddits": [
    "self",
    "DoesAnybodyElse",
    "CasualConversation",
    "rant"
  ]
}