[
  {
    "post_id": "1ml0acm",
    "subreddit": "GetMotivated",
    "post_title": "Carl Weathers' answer to the last question of his last interview (1/30/2024).  \"Any advice?\"",
    "comment": "Hey, I totally get the anxiety... It’s tough right now, especially with so much uncertainty in the air. From my own journey dealing with ADHD, I’ve learned that overthinking only adds to the stress but doesn’t change outcomes. Whatever happens, there’l haha",
    "post_score": 753
  },
  {
    "post_id": "b5bbjr",
    "subreddit": "education",
    "post_title": "Welcome to r/Education! Please read before posting!",
    "comment": "damn Imagine remembering to use the app",
    "post_score": 138
  }
]