{
  "_meta": {
    "retrieved_2nd_on": 1734571808
  },
  "all_awardings": [],
  "allow_live_comments": false,
  "approved_at_utc": null,
  "approved_by": null,
  "archived": false,
  "author": "Striking_Wrap811",
  "author_flair_background_color": null,
  "author_flair_css_class": null,
  "author_flair_richtext": [],
  "author_flair_template_id": null,
  "author_flair_text": null,
  "author_flair_text_color": null,
  "author_flair_type": "text",
  "author_fullname": "t2_11bleh8y7e",
  "author_is_blocked": false,
  "author_patreon_flair": false,
  "author_premium": false,
  "awarders": [],
  "banned_at_utc": null,
  "banned_by": null,
  "can_gild": false,
  "can_mod_post": false,
  "category": null,
  "clicked": false,
  "content_categories": null,
  "contest_mode": false,
  "created": 1734442198,
  "created_utc": 1734442198,
  "discussion_type": null,
  "distinguished": null,
  "domain": "i.redd.it",
  "downs": 0,
  "edited": false,
  "gilded": 0,
  "gildings": {},
  "hidden": false,
  "hide_score": false,
  "id": "1hgamt6",
  "is_created_from_ads_ui": false,
  "is_crosspostable": true,
  "is_meta": false,
  "is_original_content": false,
  "is_reddit_media_domain": true,
  "is_robot_indexable": true,
  "is_self": false,
  "is_video": false,
  "likes": null,
  "link_flair_background_color": "",
  "link_flair_css_class": "ds",
  "link_flair_richtext": [
    {
      "e": "text",
      "t": "Discussion"
    }
  ],
  "link_flair_template_id": "9f7ebe5c-d59d-11e3-bc67-12313d056e4a",
  "link_flair_text": "Discussion",
  "link_flair_text_color": "dark",
  "link_flair_type": "richtext",
  "locked": false,
  "media": null,
  "media_embed": {},
  "media_only": false,
  "mod_note": null,
  "mod_reason_by": null,
  "mod_reason_title": null,
  "mod_reports": [],
  "name": "t3_1hgamt6",
  "no_follow": true,
  "num_comments": 940,
  "num_crossposts": 1,
  "num_reports": null,
  "over_18": false,
  "permalink": "/r/autism/comments/1hgamt6/doesnt_everyone_hear_words_i_also_have/",
  "pinned": false,
  "post_hint": "image",
  "preview": {
    "enabled": true,
    "images": [
      {
        "id": "1zQ634sHh9R-I9tB2pNgyaYsBuXlLa_BPrpteHWAPTE",
        "resolutions": [
          {
            "height": 107,
            "url": "https://preview.redd.it/j7gwor85ve7e1.jpeg?width=108&crop=smart&auto=webp&s=655770f0d752766b685e141dd2134ea606fa5f07",
            "width": 108
          },
          {
            "height": 214,
            "url": "https://preview.redd.it/j7gwor85ve7e1.jpeg?width=216&crop=smart&auto=webp&s=2e5dc7106b169b3b9af29ab0156c789932e8bae9",
            "width": 216
          },
          {
            "height": 318,
            "url": "https://preview.redd.it/j7gwor85ve7e1.jpeg?width=320&crop=smart&auto=webp&s=9d3b41e97a8aba34b99bc437fb18b666393cbd65",
            "width": 320
          },
          {
            "height": 636,
            "url": "https://preview.redd.it/j7gwor85ve7e1.jpeg?width=640&crop=smart&auto=webp&s=c42d187d3ac00063d86fd2eca45a2a1494bac74e",
            "width": 640
          },
          {
            "height": 954,
            "url": "https://preview.redd.it/j7gwor85ve7e1.jpeg?width=960&crop=smart&auto=webp&s=a8955d8c4490b3c2a12f3ef88e800085c6d76396",
            "width": 960
          },
          {
            "height": 1073,
            "url": "https://preview.redd.it/j7gwor85ve7e1.jpeg?width=1080&crop=smart&auto=webp&s=bf1eefc9738db851a3f76ed08091f4059ac1ab4b",
            "width": 1080
          }
        ],
        "source": {
          "height": 1431,
          "url": "https://preview.redd.it/j7gwor85ve7e1.jpeg?auto=webp&s=4589595ab9d908f0d423b36d7479c287e2a7d146",
          "width": 1440
        },
        "variants": {}
      }
    ]
  },
  "pwls": null,
  "quarantine": false,
  "removal_reason": null,
  "removed_by": null,
  "removed_by_category": null,
  "report_reasons": null,
  "retrieved_on": 1734442216,
  "saved": false,
  "score": 6292,
  "secure_media": null,
  "secure_media_embed": {},
  "selftext": "",
  "send_replies": true,
  "spoiler": false,
  "stickied": false,
  "subreddit": "autism",
  "subreddit_id": "t5_2qhs6",
  "subreddit_name_prefixed": "r/autism",
  "subreddit_subscribers": 417221,
  "subreddit_type": "public",
  "suggested_sort": null,
  "thumbnail": "https://b.thumbs.redditmedia.com/b2A5hnXvYMst4BDoPX0Mzkqm2Fsq6bBfR0gTEIh0rEE.jpg",
  "thumbnail_height": 139,
  "thumbnail_width": 140,
  "title": "Doesn't everyone hear words? I also have synesthesia where I see \"subtitles\". ",
  "top_awarded_type": null,
  "total_awards_received": 0,
  "treatment_tags": [],
  "ups": 6292,
  "upvote_ratio": 0.9399999976158142,
  "url": "https://i.redd.it/j7gwor85ve7e1.jpeg",
  "url_overridden_by_dest": "https://i.redd.it/j7gwor85ve7e1.jpeg",
  "user_reports": [],
  "view_count": null,
  "visited": false,
  "wls": null,
  "alternative_subreddits": [
    "NoStupidQuestions",
    "DoesAnybodyElse",
    "self",
    "CasualConversation"
  ]
}