{
  "_meta": {
    "retrieved_2nd_on": 1731365132
  },
  "all_awardings": [],
  "allow_live_comments": false,
  "approved_at_utc": null,
  "approved_by": null,
  "archived": false,
  "author": "No_Albatross_5342",
  "author_flair_background_color": null,
  "author_flair_css_class": null,
  "author_flair_richtext": [],
  "author_flair_template_id": null,
  "author_flair_text": null,
  "author_flair_text_color": null,
  "author_flair_type": "text",
  "author_fullname": "t2_15ehggeuxs",
  "author_is_blocked": false,
  "author_patreon_flair": false,
  "author_premium": false,
  "awarders": [],
  "banned_at_utc": null,
  "banned_by": null,
  "can_gild": false,
  "can_mod_post": false,
  "category": null,
  "clicked": false,
  "content_categories": null,
  "contest_mode": false,
  "created": 1731235519,
  "created_utc": 1731235519,
  "discussion_type": null,
  "distinguished": null,
  "domain": "self.getdisciplined",
  "downs": 0,
  "edited": false,
  "gilded": 0,
  "gildings": {},
  "hidden": false,
  "hide_score": false,
  "id": "1gny0po",
  "is_created_from_ads_ui": false,
  "is_crosspostable": true,
  "is_meta": false,
  "is_original_content": false,
  "is_reddit_media_domain": false,
  "is_robot_indexable": true,
  "is_self": true,
  "is_video": false,
  "likes": null,
  "link_flair_background_color": "#2a9d8f",
  "link_flair_css_class": "",
  "link_flair_richtext": [],
  "link_flair_template_id": "a1e3e100-0a20-11ef-8188-c29d7f9c26ac",
  "link_flair_text": "💬 Discussion",
  "link_flair_text_color": "light",
  "link_flair_type": "text",
  "locked": false,
  "media": null,
  "media_embed": {},
  "media_only": false,
  "mod_note": null,
  "mod_reason_by": null,
  "mod_reason_title": null,
  "mod_reports": [],
  "name": "t3_1gny0po",
  "no_follow": true,
  "num_comments": 62,
  "num_crossposts": 0,
  "num_reports": null,
  "over_18": false,
  "permalink": "/r/getdisciplined/comments/1gny0po/realisation_being_fit_working_hard_eating_clean/",
  "pinned": false,
  "pwls": 6,
  "quarantine": false,
  "removal_reason": null,
  "removed_by": null,
  "removed_by_category": null,
  "report_reasons": null,
  "retrieved_on": 1731235536,
  "saved": false,
  "score": 1234,
  "secure_media": null,
  "secure_media_embed": {},
  "selftext": "I guess everything requires sacrifices and life is all about trade offs. I have very less time left to enjoy things, socialise or travel.",
  "send_replies": true,
  "spoiler": false,
  "stickied": false,
  "subreddit": "getdisciplined",
  "subreddit_id": "t5_2uzju",
  "subreddit_name_prefixed": "r/getdisciplined",
  "subreddit_subscribers": 1759735,
  "subreddit_type": "public",
  "suggested_sort": null,
  "thumbnail": "self",
  "thumbnail_height": null,
  "thumbnail_width": null,
  "title": "Realisation: Being fit, working hard, eating clean consumes a lot of time.",
  "top_awarded_type": null,
  "total_awards_received": 0,
  "treatment_tags": [],
  "ups": 1234,
  "upvote_ratio": 0.9800000190734863,
  "url": "https://www.reddit.com/r/getdisciplined/comments/1gny0po/realisation_being_fit_working_hard_eating_clean/",
  "user_reports": [],
  "view_count": null,
  "visited": false,
  "wls": 6,
  "alternative_subreddits": [
    "stopprocrastinating",
    "bulletjournal",
    "declutter",
    "minimalism",
    "selfimprovement",
    "college",
    "bipolar",
    "schizophrenia",
    "selfcare",
    "Meditation"
  ]
}