{
  "id": "1g96xye",
  "title": "Does anyone stay up late for no reason?",
  "selftext": "Anyone else stay up stupidly late either scrolling social media, researching something, or just doing something that it really quite pointless and doesn’t need to be done at that time. \n\nAnd I mean staying up until 3am when you have to be up at 6/7am. For no reason!!! \n\nI then feel so annoyed at myself the next day and vow to not do it again but I still do!! \n\nAny tips for stopping this?",
  "score": 2235,
  "num_comments": 363,
  "subreddit": "adhdwomen",
  "author": "poppybryan6",
  "created_utc": 1729561832,
  "url": "https://reddit.com/r/adhdwomen/comments/1g96xye",
  "is_text_post": true,
  "rank": 76
}